Workbook
Name CASE: [1]LBO!$E$7
Name CIRC: [1]LBO!$E$6
Name PIK: [1]LBO!$E$8

Sheet LBO
B2: Hillside Private Capital - Husky Blue Diagnostics LBO Model
A4: x | B4: Assumptions
B6: Entry ($MM) | G6: Financials | L6: Capital Structure | N6: Amount | O6: 2026P Int. | P6: 2027P Int. | Q6: 2028P Int. | R6: 2029P Int. | S6: 2030P Int.
B7: LTM EBITDA | E7: =11.5259 -> 11.5259 | G7: Upside Investment Case | L7: Unitranche Term Loan | N7: 5 | O7: =4.5% + V9 -> 0.0814 | P7: =4.5% + V10 -> 0.0809 | Q7: =4.5% + V11 -> 0.08 | R7: =4.5% + V12 -> 0.08 | S7: =4.5% + V13 -> 0.08 | U7: Rate Inputs
B8: EBITDA Multiple | E8: 8.5 | G8: Revenue | J8: 68.38 | U8: Year | V8: SOFR | X8: Notes
B9: Enterprise Value | E9: =E7*E8 -> 97.97015 | G9: EBITDA | J9: 11.5259 | U9: Year 1 | V9: 0.0364 | X9: 65% recurring compliance revenue
B10: Existing Net Debt | E10: 13 | G10: D&A | J10: 2.85 | L10: For Reference | U10: Year 2 | V10: 0.0359 | X10: 60% of customer base renews in 2027
B11: Equity Value | E11: =E9-E10 -> 84.97015 | G11: Capex | J11: 5.1285 | L11: IRR | O11: =O109 -> 0.2226171 | U11: Year 3 | V11: 0.035 | X11: Existing net debt to refi = $13.0mm
B12: Transaction Fees & Expenses | E12: =0.02*E27 -> 1.1003458 | G12: NWC | J12: 1.7095 | U12: Year 4 | V12: 0.035 | X12: No mandatory amortization
U13: Year 5 | V13: 0.035 | X13: Debt fees = 1.0%; sponsor fees = 2.0%
G14: Operating Assumptions
B15: Exit ($MM) | G15: YoY margin expansion | J15: 0.01
B16: EBITDA Multiple | E16: 8.5 | G16: Tax Rate | J16: 0.21
A19: x | B19: Sources and Uses
B21: Sources | J21: Uses
E22: Amount | F22: xEBITDA | G22: % Capital | M22: Amount | N22: xEBITDA | O22: % Capital
B23: Unitranche Term Loan | E23: =N7*$E$7 -> 57.6295 | F23: =E23/$E$7 -> 5 | G23: =E23/$E$29 -> 0.51159469 | J23: Purchase Price | M23: =E9 -> 97.97015 | N23: =M23/$E$7 -> 8.5 | O23: =M23/$M$29 -> 0.86971097
J24: Refi Existing Net Debt | M24: =E10 -> 13 | N24: =M24/$E$7 -> 1.1278946 | O24: =M24/$M$29 -> 0.11540497
B25: Total Debt | E25: =SUM(E23:E24) -> 57.6295 | F25: =SUM(F23:F24) -> 5 | G25: =SUM(G23:G24) -> 0.51159469 | J25: Debt Fees | M25: =J15*E25 -> 0.576295 | N25: =M25/$E$7 -> 0.05 | O25: =M25/$M$29 -> 0.0051159469
J26: Transaction Fees | M26: =E12 -> 1.1003458 | N26: =M26/$E$7 -> 0.095467236 | O26: =M26/$M$29 -> 0.0097681062
B27: Sponsor Equity | E27: =M29-E25 -> 55.017291 | F27: =E27/$E$7 -> 4.7733618 | G27: =E27/$E$29 -> 0.48840531
B29: Total Sources | E29: =SUM(E25:E27) -> 112.64679 | F29: =SUM(F25:F27) -> 9.7733618 | G29: =SUM(G25:G27) -> 1 | J29: Total Uses | M29: =SUM(M23:M26) -> 112.64679 | N29: =SUM(N23:N26) -> 9.7733618 | O29: =SUM(O23:O26) -> 1
A32: x | B32: Financials
B34: Operating Model | J34: 2025A | K34: 2026P | L34: 2027P | M34: 2028P | N34: 2029P | O34: 2030P
B35: Revenue | J35: =J8 -> 68.38 | K35: =J35*(1+J36) -> 74.8761 | L35: =K35*(1+K36) -> 81.614949 | M35: =L35*(1+L36) -> 88.960294 | N35: =M35*(1+M36) -> 97.856324 | O35: =N35*(1+N36) -> 108.62052
B36: % growth | J36: 0.095 | K36: 0.09 | L36: 0.09 | M36: 0.1 | N36: 0.11 | O36: 0.1 | Q36: 0.01 | R36: < 2027 step-up | T36: 0.01 | U36: < 2028 stepup
B38: EBITDA | J38: =J9 -> 11.5259 | K38: =K35*K39 -> 11.456043 | L38: =L35*L39 -> 13.874541 | M38: =M35*M39 -> 15.568052 | N38: =N35*N39 -> 17.614138 | O38: =O35*O39 -> 18.79135
B39: % sales | J39: =J9/J8 -> 0.1685566 | K39: 0.153 | L39: 0.17 | M39: 0.175 | N39: 0.18 | O39: 0.173
B41: EBIT | J41: =J38-J56 -> 8.6759 | K41: =K38-K56 -> 8.3060433 | L41: =L38-L56 -> 10.474541 | M41: =M38-M56 -> 11.918052 | N41: =N38-N56 -> 13.734138 | O41: =O38-O56 -> 14.75615
B42: % sales | J42: =J41/J35 -> 0.12687774 | K42: =K41/K35 -> 0.1109305 | L42: =L41/L35 -> 0.12834097 | M42: =M41/M35 -> 0.13397046 | N42: =N41/N35 -> 0.14035003 | O42: =O41/O35 -> 0.13585048
B44: Interest | J44: 0 | K44: =K92 -> 4.6910413 | L44: =L92 -> 4.5589976 | M44: =M92 -> 4.2681856 | N44: =N92 -> 3.9350018 | O44: =O92 -> 3.4935105
B46: EBT | J46: =J41-J44 -> 8.6759 | K46: =K41-K44 -> 3.615002 | L46: =L41-L44 -> 5.9155437 | M46: =M41-M44 -> 7.6498659 | N46: =N41-N44 -> 9.7991364 | O46: =O41-O44 -> 11.262639
B47: % sales | J47: =J46/J35 -> 0.12687774 | K47: =K46/K35 -> 0.048279785 | L47: =L46/L35 -> 0.07248113 | M47: =M46/M35 -> 0.085991913 | N47: =N46/N35 -> 0.100138 | O47: =O46/O35 -> 0.10368795
B49: Taxes | J49: =$J$16 * J46 -> 1.821939 | K49: =MAX(0,K46*K50) -> 0.75915042 | L49: =MAX(0,L46*L50) -> 1.2422642 | M49: =MAX(0,M46*M50) -> 1.6064718 | N49: =MAX(0,N46*N50) -> 2.0578187 | O49: =MAX(0,O46*O50) -> 2.3651543
B50: % tax rate | J50: =$J$16 -> 0.21 | K50: =$J$16 -> 0.21 | L50: =$J$16 -> 0.21 | M50: =$J$16 -> 0.21 | N50: =$J$16 -> 0.21 | O50: =$J$16 -> 0.21
B52: Net Income | J52: =J46-J49 -> 6.853961 | K52: =K46-K49 -> 2.8558516 | L52: =L46-L49 -> 4.6732796 | M52: =M46-M49 -> 6.043394 | N52: =N46-N49 -> 7.7413178 | O52: =O46-O49 -> 8.8974851
B53: % sales | J53: =J52/J35 -> 0.10023342 | K53: =K52/K35 -> 0.03814103 | L53: =L52/L35 -> 0.057260093 | M53: =M52/M35 -> 0.067933611 | N53: =N52/N35 -> 0.079109019 | O53: =O52/O35 -> 0.081913483
A55: x | B55: Cash flow Items | J55: Year 0 | K55: Year 1 | L55: Year 2 | M55: Year 3 | N55: Year 4 | O55: Year 5
B56: D&A | J56: 2.85 | K56: 3.15 | L56: 3.4 | M56: 3.65 | N56: 3.88 | O56: 4.0352
B57: % sales | J57: =J56/J35 -> 0.041678853 | K57: =K56/K35 -> 0.042069499 | L57: =L56/L35 -> 0.041659035 | M57: =M56/M35 -> 0.04102954 | N57: =N56/N35 -> 0.039649967 | O57: =O56/O35 -> 0.037149519
B59: Net Working Capital | J59: =J35*J60 -> 1.7095 | K59: =K35*K60 -> 1.9467786 | L59: =L35*L60 -> 2.1219887 | M59: =M35*M60 -> 2.3129677 | N59: =N35*N60 -> 2.5442644 | O59: =O35*O60 -> 2.8241335
B60: % sales | J60: =J12/J8 -> 0.025 | K60: 0.026 | L60: 0.026 | M60: 0.026 | N60: 0.026 | O60: 0.026
B61: Change in Net Working Capital | K61: =K59-J59 -> 0.2372786 | L61: =L59-K59 -> 0.17521007 | M61: =M59-L59 -> 0.19097898 | N61: =N59-M59 -> 0.23129677 | O61: =O59-N59 -> 0.27986909
B63: CapEx | J63: =J35*J64 -> 5.1285 | K63: =K35*K64 -> 4.492566 | L63: =L35*L64 -> 4.8968969 | M63: =M35*M64 -> 5.3376177 | N63: =N35*N64 -> 5.8713794 | O63: =O35*O64 -> 6.5172312
B64: % sales | J64: 0.075 | K64: 0.06 | L64: 0.06 | M64: 0.06 | N64: 0.06 | O64: 0.06
A66: x | B66: Levered Cash Flow | J66: Year 0 | K66: Year 1 | L66: Year 2 | M66: Year 3 | N66: Year 4 | O66: Year 5
B67: Net Income | J67: =J52 -> 6.853961 | K67: =K52 -> 2.8558516 | L67: =L52 -> 4.6732796 | M67: =M52 -> 6.043394 | N67: =N52 -> 7.7413178 | O67: =O52 -> 8.8974851
B68: D&A | J68: =J56 -> 2.85 | K68: =K56 -> 3.15 | L68: =L56 -> 3.4 | M68: =M56 -> 3.65 | N68: =N56 -> 3.88 | O68: =O56 -> 4.0352
B69: CapEx | J69: =-J63 -> -5.1285 | K69: =-K63 -> -4.492566 | L69: =-L63 -> -4.8968969 | M69: =-M63 -> -5.3376177 | N69: =-N63 -> -5.8713794 | O69: =-O63 -> -6.5172312
B70: Change in NWC | J70: 0 | K70: =-K61 -> -0.2372786 | L70: =-L61 -> -0.17521007 | M70: =-M61 -> -0.19097898 | N70: =-N61 -> -0.23129677 | O70: =-O61 -> -0.27986909
B71: Levered Cash Flow | J71: =J67+J68+J69 -> 4.575461 | K71: =K67+K68+K69+K70 -> 1.276007 | L71: =L67+L68+L69+L70 -> 3.0011725 | M71: =M67+M68+M69+M70 -> 4.1647974 | N71: =N67+N68+N69+N70 -> 5.5186416 | O71: =O67+O68+O69+O70 -> 6.1355848
B74: Credit and Leverage Ratios
B75: Debt/EBITDA | J75: =J84/J38 -> 5 | K75: =K84/K38 -> 5.030489 | L75: =L84/L38 -> 4.0616473 | M75: =M84/M38 -> 3.427039 | N75: =N84/N38 -> 2.7925024 | O75: =O84/O38 -> 2.3238821
B76: Fixed Charge Coverage Ratio | K76: =IF((K38-K63-K49)/(K44)<1.2,"Cov Breach",(K38-K63-K49)/(K44)) -> 1.3225905 | L76: =IF((L38-L63-L49)/(L44)<1.2,"Cov Breach",(L38-L63-L49)/(L44)) -> 1.6967283 | M76: =IF((M38-M63-M49)/(M44)<1.2,"Cov Breach",(M38-M63-M49)/(M44)) -> 2.0205218 | N76: =IF((N38-N63-N49)/(N44)<1.2,"Cov Breach",(N38-N63-N49)/(N44)) -> 2.4612289 | O76: =IF((O38-O63-O49)/(O44)<1.2,"Cov Breach",(O38-O63-O49)/(O44)) -> 2.8363918 | Q76: Seeking > 1.4
B77: Debt Service Coverage Ratio (EBITDA/(Paydown + Interest) | K77: =K38/(K93+K44) -> 1.9198845 | L77: =L38/(L93+L44) -> 1.8352155 | M77: =M38/(M93+M44) -> 1.8460907 | N77: =N38/(N93+N44) -> 1.8632116 | O77: =O38/(O93+O44) -> 1.9515177 | Q77: Seeking > 1.2
A80: x | B80: Debt Schedule
J82: Year 0 | K82: Year 1 | L82: Year 2 | M82: Year 3 | N82: Year 4 | O82: Year 5
B83: Unitranche Term Loan
B84: Beginning Balance | J84: =E23 -> 57.6295 | K84: =J87 -> 57.6295 | L84: =K87 -> 56.353493 | M84: =L87 -> 53.35232 | N84: =M87 -> 49.187523 | O84: =N87 -> 43.668881
B85: Interest | J85: 0 | K85: =K84*O7 -> 4.6910413 | L85: =L84*P7 -> 4.5589976 | M85: =M84*Q7 -> 4.2681856 | N85: =N84*R7 -> 3.9350018 | O85: =O84*S7 -> 3.4935105
B86: Paydown | J86: 0 | K86: =MIN(K84,MAX(0,K71)) -> 1.276007 | L86: =MIN(L84,MAX(0,L71)) -> 3.0011725 | M86: =MIN(M84,MAX(0,M71)) -> 4.1647974 | N86: =MIN(N84,MAX(0,N71)) -> 5.5186416 | O86: =MIN(O84,MAX(0,O71)) -> 6.1355848
B87: Ending Balance | J87: =J84 -> 57.6295 | K87: =K84-K86 -> 56.353493 | L87: =L84-L86 -> 53.35232 | M87: =M84-M86 -> 49.187523 | N87: =N84-N86 -> 43.668881 | O87: =O84-O86 -> 37.533297
B90: Total Debt
B91: Beginning Balance | J91: =J84 -> 57.6295 | K91: =J94 -> 57.6295 | L91: =K94 -> 56.353493 | M91: =L94 -> 53.35232 | N91: =M94 -> 49.187523 | O91: =N94 -> 43.668881
B92: Interest | J92: 0 | K92: =K85 -> 4.6910413 | L92: =L85 -> 4.5589976 | M92: =M85 -> 4.2681856 | N92: =N85 -> 3.9350018 | O92: =O85 -> 3.4935105
B93: Paydown | J93: 0 | K93: =K86 -> 1.276007 | L93: =L86 -> 3.0011725 | M93: =M86 -> 4.1647974 | N93: =N86 -> 5.5186416 | O93: =O86 -> 6.1355848
B94: Ending Balance | J94: =J87 -> 57.6295 | K94: =K87 -> 56.353493 | L94: =L87 -> 53.35232 | M94: =M87 -> 49.187523 | N94: =N87 -> 43.668881 | O94: =O87 -> 37.533297
A95: x
B96: IRR
B98: EBITDA at Exit | J98: =O38 -> 18.79135
B99: Exit Multiple | J99: =E16 -> 8.5
B100: Enterprise Value | J100: =J98*J99 -> 159.72647
B101: Net Debt | J101: =O94 -> 37.533297
B102: Sponsor Equity Value | J102: =J100-J101 -> 122.19318
J104: =E27 -> 55.017291
J106: 46022 | K106: =EOMONTH(J106,12) -> 46387 | L106: =EOMONTH(K106,12) -> 46752 | M106: =EOMONTH(L106,12) -> 47118 | N106: =EOMONTH(M106,12) -> 47483 | O106: =EOMONTH(N106,12) -> 47848
B107: Sponsor Equity at Entry | J107: =-E27 -> -55.017291 | K107: 0 | L107: 0 | M107: 0 | N107: 0 | O107: =J102 -> 122.19318
A108: x | B108: MOIC | O108: =O107/J104 -> 2.7333262
B109: IRR | J109: =XIRR(J107:O107,J106:O106) -> 0.2226171 | O109: =XIRR(J107:O107,J106:O106) -> 0.2226171
B112: Debt Returns
B114: Unitranche Debt | J114: =J106 -> 46022 | K114: =K106 -> 46387 | L114: =L106 -> 46752 | M114: =M106 -> 47118 | N114: =N106 -> 47483 | O114: =O106 -> 47848
B115: (-) Initial Capital Injection | J115: =-J84 -> -57.6295
B116: (+) Paydown | K116: =K86 -> 1.276007 | L116: =L86 -> 3.0011725 | M116: =M86 -> 4.1647974 | N116: =N86 -> 5.5186416 | O116: =O86 -> 6.1355848
B117: (+) Interest | K117: =K85 -> 4.6910413 | L117: =L85 -> 4.5589976 | M117: =M85 -> 4.2681856 | N117: =N85 -> 3.9350018 | O117: =O85 -> 3.4935105
B118: (+) Maturity | O118: =O87 -> 37.533297
B119: Total Cash Flows | J119: =SUM(J115:J118) -> -57.6295 | K119: =SUM(K115:K118) -> 5.9670483 | L119: =SUM(L115:L118) -> 7.5601701 | M119: =SUM(M115:M118) -> 8.432983 | N119: =SUM(N115:N118) -> 9.4536434 | O119: =SUM(O115:O118) -> 47.162392
B120: IRR | J120: =IRR(J119:O119) -> 0.080563457

Sheet Stress Test
B2: HPC LBO — Stress Test Operating Model | Management / Base / Downside
B4: SECTION 1 — CASE ASSUMPTIONS (Blue = inputs | Green = linked from LBO)
B5: Driver | C5: Base | D5: Upside | E5: Downside
B6: Active Case → | C6: UPSIDE | D6: ← Type: Base / Upside / Downside
B7: ▸ Revenue Growth
B8: Revenue Growth Yr1 | C8: 0.08 | D8: 0.09 | E8: 0.05
B9: Revenue Growth Yr2 | C9: 0.06 | D9: 0.09 | E9: 0.03
B10: Revenue Growth Yr3 | C10: 0.05 | D10: 0.1 | E10: 0.02
B11: Revenue Growth Yr4 | C11: 0.05 | D11: 0.11 | E11: 0.02
B12: Revenue Growth Yr5 | C12: 0.04 | D12: 0.1 | E12: 0.02
B13: ▸ EBITDA Margin
B14: Entry EBITDA Margin | C14: 0.153 | D14: 0.153 | E14: 0.14
B15: Yr2 Margin | C15: 0.158 | D15: 0.158 | E15: 0.145
B16: Yr3 Margin | C16: 0.163 | D16: 0.163 | E16: 0.15
B17: Yr4 Margin | C17: 0.168 | D17: 0.168 | E17: 0.155
B18: Yr5 Margin | C18: 0.168 | D18: 0.173 | E18: 0.155
B19: ▸ CapEx, NWC & Exit
B20: CapEx Yr1 % Rev | C20: 0.065 | D20: 0.06 | E20: 0.075
B21: CapEx Yr2-5 % Rev | C21: 0.06 | D21: 0.06 | E21: 0.075
B22: NWC % Rev | C22: 0.026 | D22: 0.026 | E22: 0.028
B23: Exit EV/EBITDA | C23: 8.5 | D23: 8.5 | E23: 8.5
B24: ▸ Fixed Inputs (linked from LBO)
B25: LTM EBITDA ($MM) | C25: =LBO!E7 -> 11.5259
B26: Entry EV/EBITDA | C26: =LBO!E8 -> 8.5
B27: Initial Debt ($MM) | C27: =LBO!E23 -> 57.6295
B28: Sponsor Equity ($MM) | C28: =LBO!E27 -> 55.017291
B29: Entry NWC ($MM) | C29: =LBO!J12 -> 1.7095
B31: SECTION 2 — OPERATING MODEL (mirrors LBO structure)
C32: Year 1 | D32: Year 2 | E32: Year 3 | F32: Year 4 | G32: Year 5 | I32: Returns Summary | J32: Mgmt | K32: Base | L32: Downside
B33: ▸ Revenue ($MM) | I33: EXIT METRICS
B34: Management | C34: =LBO!J8*(1+C8) -> 73.8504 | D34: =C34*(1+C9) -> 78.281424 | E34: =D34*(1+C10) -> 82.195495 | F34: =E34*(1+C11) -> 86.30527 | G34: =F34*(1+C12) -> 89.757481 | I34: Exit EBITDA ($MM) | J34: =C114 -> 15.079257 | K34: =D114 -> 18.79135 | L34: =E114 -> 12.16432
B35: Base | C35: =LBO!K35 -> 74.8761 | D35: =LBO!L35 -> 81.614949 | E35: =LBO!M35 -> 88.960294 | F35: =LBO!N35 -> 97.856324 | G35: =LBO!O35 -> 108.62052 | I35: Exit EV/EBITDA | J35: =C115 -> 8.5 | K35: =D115 -> 8.5 | L35: =E115 -> 8.5
B36: Downside | C36: =LBO!J8*(1+E8) -> 71.799 | D36: =C36*(1+E9) -> 73.95297 | E36: =D36*(1+E10) -> 75.432029 | F36: =E36*(1+E11) -> 76.94067 | G36: =F36*(1+E12) -> 78.479483 | I36: Exit EV ($MM) | J36: =C116 -> 128.17368 | K36: =D116 -> 159.72647 | L36: =E116 -> 103.39672
B37: ▸ EBITDA ($MM) | I37: Net Debt at Exit ($MM) | J37: =C117 -> 43.904701 | K37: =D117 -> 37.533297 | L37: =E117 -> 56.018771
B38: Management | C38: =C34*C14 -> 11.299111 | D38: =D34*C15 -> 12.368465 | E38: =E34*C16 -> 13.397866 | F38: =F34*C17 -> 14.499285 | G38: =G34*C18 -> 15.079257 | I38: Equity Value ($MM) | J38: =C118 -> 84.268981 | K38: =D118 -> 122.19318 | L38: =E118 -> 47.377948
B39: Base | C39: =LBO!K38 -> 11.456043 | D39: =LBO!L38 -> 13.874541 | E39: =LBO!M38 -> 15.568052 | F39: =LBO!N38 -> 17.614138 | G39: =LBO!O38 -> 18.79135
B40: Downside | C40: =C36*E14 -> 10.05186 | D40: =D36*E15 -> 10.723181 | E40: =E36*E16 -> 11.314804 | F40: =F36*E17 -> 11.925804 | G40: =G36*E18 -> 12.16432 | I40: RETURNS
B41: ▸ EBITDA Margin (%) | I41: Equity MOIC | J41: =C119 -> 1.5316818 | K41: =D119 -> 2.2209959 | L41: =E119 -> 0.86114652
B42: Management | C42: =C38/C34 -> 0.153 | D42: =D38/D34 -> 0.158 | E42: =E38/E34 -> 0.163 | F42: =F38/F34 -> 0.168 | G42: =G38/G34 -> 0.168 | I42: Equity IRR (XIRR) | J42: =C124 -> 0.088963762 | K42: =D124 -> 0.2226171 | L42: =E124 -> -0.029439703
B43: Base | C43: =C39/C35 -> 0.153 | D43: =D39/D35 -> 0.17 | E43: =E39/E35 -> 0.175 | F43: =F39/F35 -> 0.18 | G43: =G39/G35 -> 0.173 | I43: Debt IRR | J43: =C125 -> 0.080563457 | K43: =D125 -> 0.080563457 | L43: =E125 -> 0.080563457
B44: Downside | C44: =C40/C36 -> 0.14 | D44: =D40/D36 -> 0.145 | E44: =E40/E36 -> 0.15 | F44: =F40/F36 -> 0.155 | G44: =G40/G36 -> 0.155
B45: ▸ D&A ($MM) | I45: LEVERAGE
B46: Management | C46: 3.15 | D46: 3.4 | E46: 3.65 | F46: 3.88 | G46: 4.0352 | I46: Entry Debt/EBITDA | J46: =C126 -> 5 | K46: =D126 -> 5 | L46: =E126 -> 5
B47: Base | C47: =LBO!K56 -> 3.15 | D47: =LBO!L56 -> 3.4 | E47: =LBO!M56 -> 3.65 | F47: =LBO!N56 -> 3.88 | G47: =LBO!O56 -> 4.0352 | I47: Exit Debt/EBITDA | J47: =C127 -> 2.9115958 | K47: =D127 -> 1.997371 | L47: =E127 -> 4.6051708
B48: Downside | C48: =C36*0.04 -> 2.87196 | D48: =D36*0.04 -> 2.9581188 | E48: =E36*0.04 -> 3.0172812 | F48: =F36*0.04 -> 3.0776268 | G48: =G36*0.04 -> 3.1391793 | I48: Int. Coverage (Yr5) | J48: =C128 -> 3.9149303 | K48: =D128 -> 5.3789304 | L48: =E128 -> 2.6783818
B49: ▸ EBIT ($MM)
B50: Management | C50: =C38-C46 -> 8.1491112 | D50: =D38-D46 -> 8.968465 | E50: =E38-E46 -> 9.7478657 | F50: =F38-F46 -> 10.619285 | G50: =G38-G46 -> 11.044057
B51: Base | C51: =LBO!K41 -> 8.3060433 | D51: =LBO!L41 -> 10.474541 | E51: =LBO!M41 -> 11.918052 | F51: =LBO!N41 -> 13.734138 | G51: =LBO!O41 -> 14.75615
B52: Downside | C52: =C40-C48 -> 7.1799 | D52: =D40-D48 -> 7.7650618 | E52: =E40-E48 -> 8.2975232 | F52: =F40-F48 -> 8.848177 | G52: =G40-G48 -> 9.0251406
B53: ▸ Interest Expense ($MM)
B54: Management | C54: =C90*LBO!O7 -> 4.6910413 | D54: =D90*LBO!P7 -> 4.5917636 | E54: =E90*LBO!Q7 -> 4.3770407 | F54: =F90*LBO!R7 -> 4.1482842 | G54: =G90*LBO!S7 -> 3.8517306
B55: Base | C55: =LBO!K44 -> 4.6910413 | D55: =LBO!L44 -> 4.5589976 | E55: =LBO!M44 -> 4.2681856 | F55: =LBO!N44 -> 3.9350018 | G55: =LBO!O44 -> 3.4935105
B56: Downside | C56: =C92*LBO!O7 -> 4.6910413 | D56: =D92*LBO!P7 -> 4.6622265 | E56: =E92*LBO!Q7 -> 4.61036 | F56: =F92*LBO!R7 -> 4.5918541 | G56: =G92*LBO!S7 -> 4.5416677
B57: ▸ EBT ($MM)
B58: Management | C58: =C50-C54 -> 3.4580699 | D58: =D50-D54 -> 4.3767014 | E58: =E50-E54 -> 5.370825 | F58: =F50-F54 -> 6.4710011 | G58: =G50-G54 -> 7.1923262
B59: Base | C59: =LBO!K46 -> 3.615002 | D59: =LBO!L46 -> 5.9155437 | E59: =LBO!M46 -> 7.6498659 | F59: =LBO!N46 -> 9.7991364 | G59: =LBO!O46 -> 11.262639
B60: Downside | C60: =C52-C56 -> 2.4888587 | D60: =D52-D56 -> 3.1028353 | E60: =E52-E56 -> 3.6871632 | F60: =F52-F56 -> 4.256323 | G60: =G52-G56 -> 4.4834729
B61: ▸ Taxes ($MM)
B62: Management | C62: =MAX(0,C58)*0.21 -> 0.72619468 | D62: =MAX(0,D58)*0.21 -> 0.9191073 | E62: =MAX(0,E58)*0.21 -> 1.1278732 | F62: =MAX(0,F58)*0.21 -> 1.3589102 | G62: =MAX(0,G58)*0.21 -> 1.5103885
B63: Base | C63: =LBO!K49 -> 0.75915042 | D63: =LBO!L49 -> 1.2422642 | E63: =LBO!M49 -> 1.6064718 | F63: =LBO!N49 -> 2.0578187 | G63: =LBO!O49 -> 2.3651543
B64: Downside | C64: =MAX(0,C60)*0.21 -> 0.52266033 | D64: =MAX(0,D60)*0.21 -> 0.65159541 | E64: =MAX(0,E60)*0.21 -> 0.77430428 | F64: =MAX(0,F60)*0.21 -> 0.89382783 | G64: =MAX(0,G60)*0.21 -> 0.94152931
B65: ▸ Net Income ($MM)
B66: Management | C66: =C58-C62 -> 2.7318752 | D66: =D58-D62 -> 3.4575941 | E66: =E58-E62 -> 4.2429517 | F66: =F58-F62 -> 5.1120909 | G66: =G58-G62 -> 5.6819377
B67: Base | C67: =LBO!K52 -> 2.8558516 | D67: =LBO!L52 -> 4.6732796 | E67: =LBO!M52 -> 6.043394 | F67: =LBO!N52 -> 7.7413178 | G67: =LBO!O52 -> 8.8974851
B68: Downside | C68: =C60-C64 -> 1.9661984 | D68: =D60-D64 -> 2.4512399 | E68: =E60-E64 -> 2.912859 | F68: =F60-F64 -> 3.3624952 | G68: =G60-G64 -> 3.5419436
B70: ▸ Cash Flow Items
B71: CapEx ($MM)
B72: Management | C72: =C34*C20 -> 4.800276 | D72: =D34*C21 -> 4.6968854 | E72: =E34*C21 -> 4.9317297 | F72: =F34*C21 -> 5.1783162 | G72: =G34*C21 -> 5.3854488
B73: Base | C73: =LBO!K63 -> 4.492566 | D73: =LBO!L63 -> 4.8968969 | E73: =LBO!M63 -> 5.3376177 | F73: =LBO!N63 -> 5.8713794 | G73: =LBO!O63 -> 6.5172312
B74: Downside | C74: =C36*E20 -> 5.384925 | D74: =D36*E21 -> 5.5464727 | E74: =E36*E21 -> 5.6574022 | F74: =F36*E21 -> 5.7705502 | G74: =G36*E21 -> 5.8859613
B75: NWC Level ($MM)
B76: Management | C76: =C34*C22 -> 1.9201104 | D76: =D34*C22 -> 2.035317 | E76: =E34*C22 -> 2.1370829 | F76: =F34*C22 -> 2.243937 | G76: =G34*C22 -> 2.3336945
B77: Base | C77: =LBO!K59 -> 1.9467786 | D77: =LBO!L59 -> 2.1219887 | E77: =LBO!M59 -> 2.3129677 | F77: =LBO!N59 -> 2.5442644 | G77: =LBO!O59 -> 2.8241335
B78: Downside | C78: =C36*E22 -> 2.010372 | D78: =D36*E22 -> 2.0706832 | E78: =E36*E22 -> 2.1120968 | F78: =F36*E22 -> 2.1543388 | G78: =G36*E22 -> 2.1974255
B79: Change in NWC ($MM)
B80: Management | C80: =C76-$C$29 -> 0.2106104 | D80: =D76-C76 -> 0.11520662 | E80: =E76-D76 -> 0.10176585 | F80: =F76-E76 -> 0.10685414 | G80: =G76-F76 -> 0.089757481
B81: Base | C81: =LBO!K61 -> 0.2372786 | D81: =LBO!L61 -> 0.17521007 | E81: =LBO!M61 -> 0.19097898 | F81: =LBO!N61 -> 0.23129677 | G81: =LBO!O61 -> 0.27986909
B82: Downside | C82: =C78-$C$29 -> 0.300872 | D82: =D78-C78 -> 0.06031116 | E82: =E78-D78 -> 0.041413663 | F82: =F78-E78 -> 0.042241936 | G82: =G78-F78 -> 0.043086775
B83: Levered Free Cash Flow ($MM)
B84: Management | C84: =C66+C46-C72-C80 -> 0.87098882 | D84: =D66+D46-D72-D80 -> 2.0455021 | E84: =E66+E46-E72-E80 -> 2.8594562 | F84: =F66+F46-F72-F80 -> 3.7069205 | G84: =G66+G46-G72-G80 -> 4.2419314
B85: Base | C85: =LBO!K71 -> 1.276007 | D85: =LBO!L71 -> 3.0011725 | E85: =LBO!M71 -> 4.1647974 | F85: =LBO!N71 -> 5.5186416 | G85: =LBO!O71 -> 6.1355848
B86: Downside | C86: =C68+C48-C74-C82 -> -0.84763863 | D86: =D68+D48-D74-D82 -> -0.19742522 | E86: =E68+E48-E74-E82 -> 0.23132426 | F86: =F68+F48-F74-F82 -> 0.62732978 | G86: =G68+G48-G74-G82 -> 0.75207491
B88: ▸ Debt Schedule ($MM) [100% cash sweep]
B89: Beginning Balance
B90: Management | C90: =$C$27 -> 57.6295 | D90: =MAX(0,C90-MAX(0,C84)) -> 56.758511 | E90: =MAX(0,D90-MAX(0,D84)) -> 54.713009 | F90: =MAX(0,E90-MAX(0,E84)) -> 51.853553 | G90: =MAX(0,F90-MAX(0,F84)) -> 48.146632
B91: Base | C91: =LBO!K84 -> 57.6295 | D91: =LBO!L84 -> 56.353493 | E91: =LBO!M84 -> 53.35232 | F91: =LBO!N84 -> 49.187523 | G91: =LBO!O84 -> 43.668881
B92: Downside | C92: =$C$27 -> 57.6295 | D92: =MAX(0,C92-MAX(0,C86)) -> 57.6295 | E92: =MAX(0,D92-MAX(0,D86)) -> 57.6295 | F92: =MAX(0,E92-MAX(0,E86)) -> 57.398176 | G92: =MAX(0,F92-MAX(0,F86)) -> 56.770846
B93: Paydown (= FCF sweep)
B94: Management | C94: =MIN(C90,MAX(0,C84)) -> 0.87098882 | D94: =MIN(D90,MAX(0,D84)) -> 2.0455021 | E94: =MIN(E90,MAX(0,E84)) -> 2.8594562 | F94: =MIN(F90,MAX(0,F84)) -> 3.7069205 | G94: =MIN(G90,MAX(0,G84)) -> 4.2419314
B95: Base | C95: =LBO!K86 -> 1.276007 | D95: =LBO!L86 -> 3.0011725 | E95: =LBO!M86 -> 4.1647974 | F95: =LBO!N86 -> 5.5186416 | G95: =LBO!O86 -> 6.1355848
B96: Downside | C96: =MIN(C92,MAX(0,C86)) -> 0 | D96: =MIN(D92,MAX(0,D86)) -> 0 | E96: =MIN(E92,MAX(0,E86)) -> 0.23132426 | F96: =MIN(F92,MAX(0,F86)) -> 0.62732978 | G96: =MIN(G92,MAX(0,G86)) -> 0.75207491
B97: Ending Balance
B98: Management | C98: =MAX(0,C90-C94) -> 56.758511 | D98: =MAX(0,D90-D94) -> 54.713009 | E98: =MAX(0,E90-E94) -> 51.853553 | F98: =MAX(0,F90-F94) -> 48.146632 | G98: =MAX(0,G90-G94) -> 43.904701
B99: Base | C99: =LBO!K87 -> 56.353493 | D99: =LBO!L87 -> 53.35232 | E99: =LBO!M87 -> 49.187523 | F99: =LBO!N87 -> 43.668881 | G99: =LBO!O87 -> 37.533297
B100: Downside | C100: =MAX(0,C92-C96) -> 57.6295 | D100: =MAX(0,D92-D96) -> 57.6295 | E100: =MAX(0,E92-E96) -> 57.398176 | F100: =MAX(0,F92-F96) -> 56.770846 | G100: =MAX(0,G92-G96) -> 56.018771
B102: ▸ Credit & Leverage Ratios
B103: Debt / EBITDA (x)
B104: Management | C104: =IFERROR(C98/C38,0) -> 5.0232722 | D104: =IFERROR(D98/D38,0) -> 4.4235893 | E104: =IFERROR(E98/E38,0) -> 3.8702846 | F104: =IFERROR(F98/F38,0) -> 3.3206211 | G104: =IFERROR(G98/G38,0) -> 2.9115958
B105: Base | C105: =IFERROR(C99/C39,0) -> 4.9191061 | D105: =IFERROR(D99/D39,0) -> 3.8453394 | E105: =IFERROR(E99/E39,0) -> 3.159517 | F105: =IFERROR(F99/F39,0) -> 2.4791949 | G105: =IFERROR(G99/G39,0) -> 1.997371
B106: Downside | C106: =IFERROR(C100/C40,0) -> 5.7332175 | D106: =IFERROR(D100/D40,0) -> 5.3742916 | E106: =IFERROR(E100/E40,0) -> 5.0728385 | F106: =IFERROR(F100/F40,0) -> 4.7603371 | G106: =IFERROR(G100/G40,0) -> 4.6051708
...

Sheet PublicComp Table
A1: Company | B1: Market Cap ($M) | C1: EV ($M) | D1: Net Debt ($M) | E1: EV / Revenue (LTM) | F1: EV / EBITDA (LTM)
A2: SGS S.A. | B2: 19654 | C2: 23112 | D2: 3575 | E2: 2.7 | F2: 13
A3: Bureau Veritas S.A. | B3: 15253 | C3: 17287 | D3: 2017 | E3: 2.2 | F3: 11.7
A4: Intertek Group PLC | B4: 10197 | C4: 11351 | D4: 1481 | E4: 2.4 | F4: 11.2
A5: Mistras Group, Inc. | B5: 251 | C5: 470 | D5: 191 | E5: 0.7 | F5: 5.6
A7: Mean | E7: =AVERAGE(E2:E5) -> 2 | F7: =AVERAGE(F2:F5) -> 10.375
A8: Median | E8: =MEDIAN(E2:E5) -> 2.3 | F8: =MEDIAN(F2:F5) -> 11.45
A9: Max | E9: =MIN(E2:E5) -> 0.7 | F9: =MIN(F2:F5) -> 5.6
A10: Min | E10: =MAX(E2:E5) -> 2.7 | F10: =MAX(F2:F5) -> 13
